README.md
licence.txt
setup.py
Great_Python_Learning.egg-info/PKG-INFO
Great_Python_Learning.egg-info/SOURCES.txt
Great_Python_Learning.egg-info/dependency_links.txt
Great_Python_Learning.egg-info/not-zip-safe
Great_Python_Learning.egg-info/top_level.txt
Text_Decoration/__init__.py
Text_Decoration/my_text.py
Text_Decoration/text_lower.py
Text_Decoration/text_title.py
Text_Decoration/text_upper.py
maths/__init__.py
maths/addition.py
maths/division.py
maths/multiplication.py
maths/my_number.py
maths/substraction.py