Metadata-Version: 2.1
Name: Great_Python_Learning
Version: 0.1
Summary: This Package has both maths & text library APIs
Author: Suresh Maha Rajashekar
Author-email: sureshmaha@greatpythonlearning.com
License-File: licence.txt
